naver/__init__.py
naver/pkgs.py
naver/template.py
naverapi/__init__.py
naverapi/auth.py
naverapi/models.py
naverapi/parser.py
naverapi/req.py
naverapi/papago/__init__.py
naverapi/search/__init__.py
naverapi/search/news.py
naverapi/search/queryword.py
naverlib/__init__.py
naverlib/batch.py
naverlib/const.py
naverlib/models.py
naverlib/parser.py
naverlib/req.py
naverlib/template.py
naversrch/__init__.py
naversrch/batch.py
naversrch/models.py
naversrch/news.py
naversrch/template.py
NaverService-0.0.1.dist-info/LICENSE
NaverService-0.0.1.dist-info/METADATA
NaverService-0.0.1.dist-info/WHEEL
NaverService-0.0.1.dist-info/top_level.txt
NaverService-0.0.1.dist-info/RECORD
