Metadata-Version: 2.1
Name: NaverService
Version: 0.0.1
Summary: innovata-NaverService
Home-page: https://github.com/innovata/NaverService
Author: innovata sambong
Author-email: iinnovata@gmail.com
License: UNKNOWN
Platform: UNKNOWN
Classifier: Programming Language :: Python :: 3
Classifier: License :: OSI Approved :: MIT License
Classifier: Operating System :: OS Independent
Requires-Python: >=3.8
License-File: LICENSE
Requires-Dist: idebug
Requires-Dist: requests
Requires-Dist: beautifulsoup4
Requires-Dist: pymongo
